nazgul/nazgul.py
test.coin_nazgul-0.1.0.dist-info/WHEEL
test.coin_nazgul-0.1.0.dist-info/METADATA
test.coin_nazgul-0.1.0.dist-info/RECORD
