Metadata-Version: 2.1
Name: test.coin-nazgul
Version: 0.1.0
Summary: 
Author: Paul Guénézan
Author-email: paul@guenezan.me
Requires-Python: >=3.10,<4.0
Classifier: Programming Language :: Python :: 3
Classifier: Programming Language :: Python :: 3.10
Requires-Dist: base58 (==2.1.1)
Requires-Dist: pynacl (==1.5.0)
Requires-Dist: test.coin-gandalf (>=0.3.0,<0.4.0)
